nanonet/extra/hilbert_transform.py
nanonet/negf/__init__.py
nanonet/negf/cfr.py
nanonet/negf/continued_fraction_representation.py
nanonet/negf/field.py
nanonet/negf/greens_functions.py
nanonet/negf/hamiltonian_chain.py
nanonet/negf/invdisttree.py
nanonet/negf/poisson.py
nanonet/negf/pole_summation_method.py
nanonet/negf/recursive_greens_functions.py
nanonet/negf/transport.py
nanonet/negf/two_terminal_device.py
nanonet/tb/__init__.py
nanonet/tb/abstract_interfaces.py
nanonet/tb/aux_functions.py
nanonet/tb/block_tridiagonalization.py
nanonet/tb/constants.py
nanonet/tb/diatomic_matrix_element.py
nanonet/tb/hamiltonian.py
nanonet/tb/hamiltonian_initializer.py
nanonet/tb/hamiltonian_sparse.py
nanonet/tb/orbitals.py
nanonet/tb/plotting.py
nanonet/tb/reduced_mode_space.py
nanonet/tb/sorting_algorithms.py
nanonet/tb/special_points.py
nanonet/tb/structure_designer.py
nanonet/tb/tb_params.py
nanonet/tb/tb_script.py
nanonet/tb/tbmpi_script.py
nanonet/verbosity/__init__.py
nanonet/verbosity/verbosity.py
nano_net-1.3.12.dist-info/LICENSE
nano_net-1.3.12.dist-info/METADATA
nano_net-1.3.12.dist-info/WHEEL
nano_net-1.3.12.dist-info/entry_points.txt
nano_net-1.3.12.dist-info/top_level.txt
nano_net-1.3.12.dist-info/RECORD
