Metadata-Version: 2.1
Name: nano-net
Version: 1.3.12
Summary: Python framework for tight-binding computations
Home-page: https://github.com/freude/NanoNet
Author: M. V. Klymenko, J. A. Vaitkus, J. S. Smith, J. H. Cole
Author-email: mike.klymenko@rmit.edu.au
License: MIT
Classifier: Programming Language :: Python :: 3
Classifier: License :: OSI Approved :: MIT License
Classifier: Operating System :: OS Independent
Requires-Python: >=3.6
License-File: LICENSE
Requires-Dist: setuptools
Requires-Dist: matplotlib
Requires-Dist: numpy
Requires-Dist: scipy
Requires-Dist: PyYAML
Requires-Dist: nose
Requires-Dist: mpi4py
Requires-Dist: future
Requires-Dist: pyfiglet
Requires-Dist: ase
